LICENSE
MANIFEST.in
README.rst
setup.cfg
setup.py
pretix_juvare_notify/__init__.py
pretix_juvare_notify/forms.py
pretix_juvare_notify/models.py
pretix_juvare_notify/signals.py
pretix_juvare_notify/tasks.py
pretix_juvare_notify/urls.py
pretix_juvare_notify/views.py
pretix_juvare_notify.egg-info/PKG-INFO
pretix_juvare_notify.egg-info/SOURCES.txt
pretix_juvare_notify.egg-info/dependency_links.txt
pretix_juvare_notify.egg-info/entry_points.txt
pretix_juvare_notify.egg-info/requires.txt
pretix_juvare_notify.egg-info/top_level.txt
pretix_juvare_notify/locale/de/LC_MESSAGES/django.po
pretix_juvare_notify/locale/de_Informal/.gitkeep
pretix_juvare_notify/locale/de_Informal/LC_MESSAGES/django.po
pretix_juvare_notify/management/__init__.py
pretix_juvare_notify/management/commands/__init__.py
pretix_juvare_notify/management/commands/juvare_export_mismatches.py
pretix_juvare_notify/migrations/0001_initial.py
pretix_juvare_notify/migrations/__init__.py
pretix_juvare_notify/static/pretix_juvare_notify/.gitkeep
pretix_juvare_notify/templates/pretix_juvare_notify/.gitkeep
pretix_juvare_notify/templates/pretix_juvare_notify/global.html
pretix_juvare_notify/templates/pretix_juvare_notify/history.html
pretix_juvare_notify/templates/pretix_juvare_notify/organizer.html
pretix_juvare_notify/templates/pretix_juvare_notify/reminders.html
pretix_juvare_notify/templates/pretix_juvare_notify/send_form.html
pretix_juvare_notify/templates/pretix_juvare_notify/settings_template_fragment.html