Metadata-Version: 1.0
Name: pretix-juvare-notify
Version: 1.1.11
Summary: Additionally to sending emails with pretix, send SMS to your customers with Juvare Notify! Uses the built-in phone number field.
Home-page: https://github.com/rixx/pretix-juvare-notify
Author: Tobias Kunze
Author-email: r@rixx.de
License: Apache
Platform: UNKNOWN
